reflexsive/__init__.py
reflexsive/cli.py
reflexsive/config.py
reflexsive/core.py
reflexsive/errors.py
reflexsive/stubgen.py
reflexsive-0.1.6.post0.dist-info/LICENSE
reflexsive-0.1.6.post0.dist-info/METADATA
reflexsive-0.1.6.post0.dist-info/WHEEL
reflexsive-0.1.6.post0.dist-info/entry_points.txt
reflexsive-0.1.6.post0.dist-info/RECORD
