Metadata-Version: 2.3
Name: reflexsive
Version: 0.1.6.post0
Summary: Method aliasing system with argument remapping and optional stub generation
License: LICENSE
Keywords: alias,aliasing,function remapping,method remapping,decorator,python,reflex
Author: Dylan Raiff
Requires-Python: >=3.10,<4
Classifier: Development Status :: 3 - Alpha
Classifier: License :: OSI Approved :: MIT License
Classifier: License :: Other/Proprietary License
Classifier: Operating System :: OS Independent
Classifier: Programming Language :: Python :: 3
Classifier: Programming Language :: Python :: 3.10
Classifier: Programming Language :: Python :: 3.11
Classifier: Programming Language :: Python :: 3.12
Classifier: Programming Language :: Python :: 3.13
Classifier: Programming Language :: Python :: 3.8
Classifier: Programming Language :: Python :: 3.9
Requires-Dist: click (>=8.2.1,<9.0.0)
Requires-Dist: pyyaml (>=6.0.2,<7.0.0)
Project-URL: Homepage, https://github.com/d-raiff/Reflex
Project-URL: Issues, https://github.com/d-raiff/Reflex/issues
Project-URL: Repository, https://github.com/d-raiff/Reflex
